requests_cloud_auth-0.0.2.dist-info/DESCRIPTION.rst
requests_cloud_auth-0.0.2.dist-info/entry_points.txt
requests_cloud_auth-0.0.2.dist-info/RECORD
requests_cloud_auth-0.0.2.dist-info/metadata.json
requests_cloud_auth-0.0.2.dist-info/WHEEL
requests_cloud_auth-0.0.2.dist-info/top_level.txt
requests_cloud_auth-0.0.2.dist-info/METADATA
requests_cloud_auth/rackspace.py
requests_cloud_auth/keystone.py
requests_cloud_auth/__init__.py
