Metadata-Version: 2.0
Name: requests-cloud-auth
Version: 0.0.2
Summary: A collection of authentication extensions for Requests
Home-page: https://github.com/jmvrbanac/requests-cloud-auth
Author: John Vrbanac
Author-email: john.vrbanac@linux.com
License: Apache v2
Keywords: requests authenication cloud keystone extensions
Platform: UNKNOWN
Classifier: Development Status :: 3 - Alpha
Classifier: Intended Audience :: Developers
Classifier: License :: OSI Approved :: Apache Software License
Classifier: Programming Language :: Python :: 2.7
Classifier: Programming Language :: Python :: 3.3
Classifier: Programming Language :: Python :: 3.4
Requires-Dist: requests (>=2.4.1)
